yt_downloader_gui/main.py
yt_downloader_gui/youtube_downloader.py
yt_downloader_gui-0.0.2.dist-info/METADATA
yt_downloader_gui-0.0.2.dist-info/WHEEL
yt_downloader_gui-0.0.2.dist-info/entry_points.txt
yt_downloader_gui-0.0.2.dist-info/RECORD
